llm_threat_hunt/__init__.py
llm_threat_hunt/cli.py
llm_threat_hunt/db.py
llm_threat_hunt/embedder.py
llm_threat_hunt/enricher.py
llm_threat_hunt/loader.py
llm_threat_hunt/pipeline.py
llm_threat_hunt/store.py
llm_hunt-0.1.0.dist-info/METADATA
llm_hunt-0.1.0.dist-info/WHEEL
llm_hunt-0.1.0.dist-info/entry_points.txt
llm_hunt-0.1.0.dist-info/top_level.txt
llm_hunt-0.1.0.dist-info/RECORD
